mqttgateway/__init__.py
mqttgateway/app_properties.py
mqttgateway/default.conf
mqttgateway/dummy2mqtt.conf
mqttgateway/dummy_interface.py
mqttgateway/dummy_map.json
mqttgateway/dummy_start.py
mqttgateway/init_logger.py
mqttgateway/load_config.py
mqttgateway/mqtt_client.py
mqttgateway/mqtt_map.py
mqttgateway/mqtt_map_schema.json
mqttgateway/start_gateway.py
mqttgateway/throttled_exception.py
mqttgateway-1.1.2.dist-info/LICENSE
mqttgateway-1.1.2.dist-info/METADATA
mqttgateway-1.1.2.dist-info/WHEEL
mqttgateway-1.1.2.dist-info/entry_points.txt
mqttgateway-1.1.2.dist-info/top_level.txt
mqttgateway-1.1.2.dist-info/RECORD
