Metadata-Version: 2.1
Name: mqttgateway
Version: 1.1.2
Summary: Framework for MQTT Gateways.
Home-page: http://mqttgateway.readthedocs.io/en/latest/
Author: Pier Paolo Taddonio
Author-email: paolo.taddonio@empiluma.com
License: MIT
Keywords: mqtt gateway
Platform: UNKNOWN
Classifier: Development Status :: 4 - Beta
Classifier: Intended Audience :: Developers
Classifier: Topic :: Software Development :: Embedded Systems
Classifier: License :: OSI Approved :: MIT License
Classifier: Programming Language :: Python :: 2.7
Classifier: Programming Language :: Python :: 3.3
Classifier: Programming Language :: Python :: 3.4
Classifier: Programming Language :: Python :: 3.5
Classifier: Programming Language :: Python :: 3.6
Classifier: Programming Language :: Python :: 3.7
Requires-Dist: paho-mqtt (>=1.4.0)
